LICENCE
MANIFEST.in
pyproject.toml
setup.py
sciborg/__init__.py
sciborg/requirements.txt
sciborg.egg-info/PKG-INFO
sciborg.egg-info/SOURCES.txt
sciborg.egg-info/dependency_links.txt
sciborg.egg-info/requires.txt
sciborg.egg-info/top_level.txt
sciborg/agents/__init__.py
sciborg/agents/agent.py
sciborg/agents/goal_conditioned/__init__.py
sciborg/agents/goal_conditioned/goal_conditioned_agent.py
sciborg/agents/goal_conditioned/goal_conditioned_wrapper.py
sciborg/agents/goal_conditioned/her.py
sciborg/agents/goal_conditioned/tilo.py
sciborg/agents/utils/__init__.py
sciborg/agents/utils/load_agent.py
sciborg/agents/utils/nn.py
sciborg/agents/utils/replay_buffer.py
sciborg/agents/value_based_agents/__init__.py
sciborg/agents/value_based_agents/ddpg.py
sciborg/agents/value_based_agents/distributional_ddpg.py
sciborg/agents/value_based_agents/distributional_dqn.py
sciborg/agents/value_based_agents/dqn.py
sciborg/agents/value_based_agents/sac.py
sciborg/agents/value_based_agents/value_based_agent.py
sciborg/environments/__init__.py
sciborg/environments/environment.py
sciborg/environments/goal_conditioned_environment.py
sciborg/environments/ant_maze/__init__.py
sciborg/environments/ant_maze/ant_maze.py
sciborg/environments/ant_maze/mujoco_model_utils.py
sciborg/environments/ant_maze/maps/HAC_four_rooms.py
sciborg/environments/ant_maze/maps/__init__.py
sciborg/environments/ant_maze/maps/empty_room.py
sciborg/environments/ant_maze/maps/empty_room_small.py
sciborg/environments/ant_maze/maps/extreme_maze.py
sciborg/environments/ant_maze/maps/four_rooms.py
sciborg/environments/ant_maze/maps/four_rooms_small.py
sciborg/environments/ant_maze/maps/four_rooms_sorb.py
sciborg/environments/ant_maze/maps/hard_maze.py
sciborg/environments/ant_maze/maps/impossible_maze.py
sciborg/environments/ant_maze/maps/join_rooms_medium.py
sciborg/environments/ant_maze/maps/maps_index.py
sciborg/environments/ant_maze/maps/medium_maze.py
sciborg/environments/ant_maze/maps/tile_type.py
sciborg/environments/ant_maze/maps/unused/__init__.py
sciborg/environments/ant_maze/maps/unused/extreme_maze.py
