Metadata-Version: 2.1
Name: sciborg
Version: 0.0.1
Summary: Reinforcement learning library for building complex agents with simple components.
Home-page: https://github.com/hbonnavaud/sciborg
Author: Hedwin BONNAVAUD
Author-email: hbonnavaud@gmail.com
License: UNKNOWN
Platform: UNKNOWN
Classifier: Programming Language :: Python :: 3
Classifier: License :: OSI Approved :: MIT License
Classifier: Operating System :: OS Independent
Requires-Python: >=3.6
License-File: LICENCE
